oa_structural_variants/__init__.py
oa_structural_variants/fusion/__init__.py
oa_structural_variants/fusion/fusion.py
oa_structural_variants/fusion/partner.py
oa_structural_variants/fusion/utils.py
oa_structural_variants/structural_variants.py
oa_structural_variants/utils.py
oa_structural_variants-0.1.0.dist-info/WHEEL
oa_structural_variants-0.1.0.dist-info/METADATA
oa_structural_variants-0.1.0.dist-info/RECORD
