Metadata-Version: 2.1
Name: oa-structural-variants
Version: 0.1.0
Summary: 
Author: Benoitdw
Author-email: bw@oncodna.com
Requires-Python: >=3.11,<4.0
Classifier: Programming Language :: Python :: 3
Classifier: Programming Language :: Python :: 3.11
Requires-Dist: dacite (>=1.8.0,<2.0.0)
Requires-Dist: dnautils (>=0.1.0,<0.2.0)
Requires-Dist: gtfparse (>=2.0.1,<3.0.0)
Requires-Dist: pandas (>=2.0.0,<3.0.0)
Requires-Dist: polars (>=0.16.18,<0.17.0)
